cacert.pem
bin/cudaq-qpud
bin/cudaq-qpud.py
bin/json_request_runner.py
bin/nvqc_proxy.py
cuda_quantum_cu11-0.12.0.post1.dist-info/licenses/CITATION.cff
cuda_quantum_cu11-0.12.0.post1.dist-info/licenses/LICENSE
cuda_quantum_cu11-0.12.0.post1.dist-info/licenses/NOTICE
cuda_quantum_cu11.libs/libgomp-870cb1d0.so.1.0.0
cudaq/__init__.py
cudaq/_metadata.py
cudaq/_packages.py
cudaq/dbg/__init__.py
cudaq/dbg/ast.py
cudaq/display/display_trace.py
cudaq/domains/__init__.py
cudaq/domains/chemistry/__init__.py
cudaq/dynamics/__init__.py
cudaq/dynamics/cudm_helpers.py
cudaq/dynamics/cudm_solver.py
cudaq/dynamics/evolution.py
cudaq/dynamics/helpers.py
cudaq/dynamics/integrator.py
cudaq/dynamics/nvqir_dynamics_bindings.cpython-313-x86_64-linux-gnu.so
cudaq/dynamics/schedule.py
cudaq/dynamics/integrators/__init__.py
cudaq/dynamics/integrators/builtin_integrators.py
cudaq/dynamics/integrators/cuda_torchdiffeq_integrator.py
cudaq/dynamics/integrators/scipy_integrators.py
cudaq/handlers/__init__.py
cudaq/handlers/photonics_kernel.py
cudaq/handlers/target_handler.py
cudaq/kernel/analysis.py
cudaq/kernel/ast_bridge.py
cudaq/kernel/captured_data.py
cudaq/kernel/kernel_builder.py
cudaq/kernel/kernel_decorator.py
cudaq/kernel/quake_value.py
cudaq/kernel/register_op.py
cudaq/kernel/utils.py
cudaq/kernel/common/fermionic_swap.py
cudaq/kernel/common/givens.py
cudaq/kernels/__init__.py
cudaq/kernels/hwe.py
cudaq/kernels/uccsd.py
cudaq/lib/__init__.py
cudaq/lib/composite_operations/fswap.py
cudaq/lib/composite_operations/givens.py
cudaq/mlir/execution_engine.py
cudaq/mlir/ir.py
cudaq/mlir/passmanager.py
cudaq/mlir/_mlir_libs/__init__.py
cudaq/mlir/_mlir_libs/_mlir.cpython-313-x86_64-linux-gnu.so
cudaq/mlir/_mlir_libs/_mlirAsyncPasses.cpython-313-x86_64-linux-gnu.so
cudaq/mlir/_mlir_libs/_mlirDialectsLinalg.cpython-313-x86_64-linux-gnu.so
cudaq/mlir/_mlir_libs/_mlirDialectsPDL.cpython-313-x86_64-linux-gnu.so
cudaq/mlir/_mlir_libs/_mlirDialectsQuant.cpython-313-x86_64-linux-gnu.so
cudaq/mlir/_mlir_libs/_mlirDialectsSparseTensor.cpython-313-x86_64-linux-gnu.so
cudaq/mlir/_mlir_libs/_mlirDialectsTransform.cpython-313-x86_64-linux-gnu.so
cuda_quantum_cu11-0.12.0.post1.dist-info/METADATA
cuda_quantum_cu11-0.12.0.post1.dist-info/WHEEL
cuda_quantum_cu11-0.12.0.post1.dist-info/RECORD
